{
  "id": "85d4c23f-3209-48c1-99ee-0dbb040b9061",
  "prevId": "db5afbd1-85bd-4151-ab4c-6285dac9ef29",
  "version": "7",
  "dialect": "postgresql",
  "tables": {
    "public.code_configs": {
      "name": "code_configs",
      "schema": "",
      "columns": {
        "id": {
          "name": "id",
          "type": "uuid",
          "primaryKey": true,
          "notNull": true,
          "default": "gen_random_uuid()"
        },
        "question_id": {
          "name": "question_id",
          "type": "uuid",
          "primaryKey": false,
          "notNull": true
        },
        "time_limit": {
          "name": "time_limit",
          "type": "integer",
          "primaryKey": false,
          "notNull": true,
          "default": 1000
        },
        "memory_limit": {
          "name": "memory_limit",
          "type": "integer",
          "primaryKey": false,
          "notNull": true,
          "default": 65536
        },
        "starter_code": {
          "name": "starter_code",
          "type": "text",
          "primaryKey": false,
          "notNull": false
        },
        "teacher_code": {
          "name": "teacher_code",
          "type": "text",
          "primaryKey": false,
          "notNull": false
        }
      },
      "indexes": {},
      "foreignKeys": {
        "code_configs_question_id_questions_id_fk": {
          "name": "code_configs_question_id_questions_id_fk",
          "tableFrom": "code_configs",
          "tableTo": "questions",
          "columnsFrom": [
            "question_id"
          ],
          "columnsTo": [
            "id"
          ],
          "onDelete": "cascade",
          "onUpdate": "no action"
        }
      },
      "compositePrimaryKeys": {},
      "uniqueConstraints": {
        "code_configs_question_id_unique": {
          "name": "code_configs_question_id_unique",
          "nullsNotDistinct": false,
          "columns": [
            "question_id"
          ]
        }
      },
      "policies": {},
      "checkConstraints": {},
      "isRLSEnabled": false
    },
    "public.exam_assignments": {
      "name": "exam_assignments",
      "schema": "",
      "columns": {
        "id": {
          "name": "id",
          "type": "uuid",
          "primaryKey": true,
          "notNull": true,
          "default": "gen_random_uuid()"
        },
        "exam_id": {
          "name": "exam_id",
          "type": "uuid",
          "primaryKey": false,
          "notNull": true
        },
        "student_id": {
          "name": "student_id",
          "type": "uuid",
          "primaryKey": false,
          "notNull": true
        }
      },
      "indexes": {
        "unique_exam_student_assignment": {
          "name": "unique_exam_student_assignment",
          "columns": [
            {
              "expression": "exam_id",
              "isExpression": false,
              "asc": true,
              "nulls": "last"
            },
            {
              "expression": "student_id",
              "isExpression": false,
              "asc": true,
              "nulls": "last"
            }
          ],
          "isUnique": true,
          "concurrently": false,
          "method": "btree",
          "with": {}
        },
        "idx_exam_assignments_lookup": {
          "name": "idx_exam_assignments_lookup",
          "columns": [
            {
              "expression": "exam_id",
              "isExpression": false,
              "asc": true,
              "nulls": "last"
            }
          ],
          "isUnique": false,
          "concurrently": false,
          "method": "btree",
          "with": {}
        }
      },
      "foreignKeys": {
        "exam_assignments_exam_id_exams_id_fk": {
          "name": "exam_assignments_exam_id_exams_id_fk",
          "tableFrom": "exam_assignments",
          "tableTo": "exams",
          "columnsFrom": [
            "exam_id"
          ],
          "columnsTo": [
            "id"
          ],
          "onDelete": "cascade",
          "onUpdate": "no action"
        },
        "exam_assignments_student_id_users_id_fk": {
          "name": "exam_assignments_student_id_users_id_fk",
          "tableFrom": "exam_assignments",
          "tableTo": "users",
          "columnsFrom": [
            "student_id"
          ],
          "columnsTo": [
            "id"
          ],
          "onDelete": "cascade",
          "onUpdate": "no action"
        }
      },
      "compositePrimaryKeys": {},
      "uniqueConstraints": {},
      "policies": {},
      "checkConstraints": {},
      "isRLSEnabled": false
    },
    "public.exam_submissions": {
      "name": "exam_submissions",
      "schema": "",
      "columns": {
        "id": {
          "name": "id",
          "type": "uuid",
          "primaryKey": true,
          "notNull": true,
          "default": "gen_random_uuid()"
        },
        "exam_id": {
          "name": "exam_id",
          "type": "uuid",
          "primaryKey": false,
          "notNull": true
        },
        "student_id": {
          "name": "student_id",
          "type": "uuid",
          "primaryKey": false,
          "notNull": true
        },
        "start_at": {
          "name": "start_at",
          "type": "timestamp with time zone",
          "primaryKey": false,
          "notNull": true,
          "default": "now()"
        },
        "question_order": {
          "name": "question_order",
          "type": "json",
          "primaryKey": false,
          "notNull": false
        },
        "submitted_at": {
          "name": "submitted_at",
          "type": "timestamp with time zone",
          "primaryKey": false,
          "notNull": false
        },
        "total_score": {
          "name": "total_score",
          "type": "numeric(5, 2)",
          "primaryKey": false,
          "notNull": false,
          "default": "'0.00'"
        },
        "client_ip": {
          "name": "client_ip",
          "type": "varchar(45)",
          "primaryKey": false,
          "notNull": true
        },
        "focus_loss_count": {
          "name": "focus_loss_count",
          "type": "integer",
          "primaryKey": false,
          "notNull": true,
          "default": 0
        },
        "close_reason": {
          "name": "close_reason",
          "type": "varchar(50)",
          "primaryKey": false,
          "notNull": false
        },
        "active_seconds": {
          "name": "active_seconds",
          "type": "integer",
          "primaryKey": false,
          "notNull": true,
          "default": 0
        },
        "attempt": {
          "name": "attempt",
          "type": "integer",
          "primaryKey": false,
          "notNull": true,
          "default": 1
        }
      },
      "indexes": {
        "one_submission_per_student_exam_attempt": {
          "name": "one_submission_per_student_exam_attempt",
          "columns": [
            {
              "expression": "exam_id",
              "isExpression": false,
              "asc": true,
              "nulls": "last"
            },
            {
              "expression": "student_id",
              "isExpression": false,
              "asc": true,
              "nulls": "last"
            },
            {
              "expression": "attempt",
              "isExpression": false,
              "asc": true,
              "nulls": "last"
            }
          ],
          "isUnique": true,
          "concurrently": false,
          "method": "btree",
          "with": {}
        },
        "idx_submissions_lookup": {
          "name": "idx_submissions_lookup",
          "columns": [
            {
              "expression": "exam_id",
              "isExpression": false,
              "asc": true,
              "nulls": "last"
            },
            {
              "expression": "student_id",
              "isExpression": false,
              "asc": true,
              "nulls": "last"
            }
          ],
          "isUnique": false,
          "concurrently": false,
          "method": "btree",
          "with": {}
        }
      },
      "foreignKeys": {
        "exam_submissions_exam_id_exams_id_fk": {
          "name": "exam_submissions_exam_id_exams_id_fk",
          "tableFrom": "exam_submissions",
          "tableTo": "exams",
          "columnsFrom": [
            "exam_id"
          ],
          "columnsTo": [
            "id"
          ],
          "onDelete": "cascade",
          "onUpdate": "no action"
        },
        "exam_submissions_student_id_users_id_fk": {
          "name": "exam_submissions_student_id_users_id_fk",
          "tableFrom": "exam_submissions",
          "tableTo": "users",
          "columnsFrom": [
            "student_id"
          ],
          "columnsTo": [
            "id"
          ],
          "onDelete": "cascade",
          "onUpdate": "no action"
        }
      },
      "compositePrimaryKeys": {},
      "uniqueConstraints": {},
      "policies": {},
      "checkConstraints": {},
      "isRLSEnabled": false
    },
    "public.exams": {
      "name": "exams",
      "schema": "",
      "columns": {
        "id": {
          "name": "id",
          "type": "uuid",
          "primaryKey": true,
          "notNull": true,
          "default": "gen_random_uuid()"
        },
        "title": {
          "name": "title",
          "type": "varchar(150)",
          "primaryKey": false,
          "notNull": true
        },
        "description": {
          "name": "description",
          "type": "text",
          "primaryKey": false,
          "notNull": false
        },
        "duration": {
          "name": "duration",
          "type": "integer",
          "primaryKey": false,
          "notNull": true
        },
        "start_time": {
          "name": "start_time",
          "type": "timestamp with time zone",
          "primaryKey": false,
          "notNull": true
        },
        "end_time": {
          "name": "end_time",
          "type": "timestamp with time zone",
          "primaryKey": false,
          "notNull": true
        },
        "is_shuffled": {
          "name": "is_shuffled",
          "type": "boolean",
          "primaryKey": false,
          "notNull": true,
          "default": false
        },
        "allowed_attempts": {
          "name": "allowed_attempts",
          "type": "integer",
          "primaryKey": false,
          "notNull": true,
          "default": 1
        },
        "access_type": {
          "name": "access_type",
          "type": "varchar(20)",
          "primaryKey": false,
          "notNull": true,
          "default": "'ALL'"
        },
        "session_type": {
          "name": "session_type",
          "type": "varchar(20)",
          "primaryKey": false,
          "notNull": true,
          "default": "'QUIZ'"
        },
        "focus_loss_policy": {
          "name": "focus_loss_policy",
          "type": "varchar(20)",
          "primaryKey": false,
          "notNull": true,
          "default": "'LOG_ONLY'"
        },
        "created_by": {
          "name": "created_by",
          "type": "uuid",
          "primaryKey": false,
          "notNull": true
        },
        "created_at": {
          "name": "created_at",
          "type": "timestamp with time zone",
          "primaryKey": false,
          "notNull": true,
          "default": "now()"
        }
      },
      "indexes": {
        "idx_exams_dates": {
          "name": "idx_exams_dates",
          "columns": [
            {
              "expression": "start_time",
              "isExpression": false,
              "asc": true,
              "nulls": "last"
            },
            {
              "expression": "end_time",
              "isExpression": false,
              "asc": true,
              "nulls": "last"
            }
          ],
          "isUnique": false,
          "concurrently": false,
          "method": "btree",
          "with": {}
        }
      },
      "foreignKeys": {
        "exams_created_by_users_id_fk": {
          "name": "exams_created_by_users_id_fk",
          "tableFrom": "exams",
          "tableTo": "users",
          "columnsFrom": [
            "created_by"
          ],
          "columnsTo": [
            "id"
          ],
          "onDelete": "cascade",
          "onUpdate": "no action"
        }
      },
      "compositePrimaryKeys": {},
      "uniqueConstraints": {},
      "policies": {},
      "checkConstraints": {},
      "isRLSEnabled": false
    },
    "public.platform_settings": {
      "name": "platform_settings",
      "schema": "",
      "columns": {
        "id": {
          "name": "id",
          "type": "uuid",
          "primaryKey": true,
          "notNull": true,
          "default": "gen_random_uuid()"
        },
        "piston_api_url": {
          "name": "piston_api_url",
          "type": "varchar(255)",
          "primaryKey": false,
          "notNull": true,
          "default": "'https://emkc.org/api/v2/piston'"
        },
        "queue_backend": {
          "name": "queue_backend",
          "type": "varchar(100)",
          "primaryKey": false,
          "notNull": true,
          "default": "'Upstash Redis'"
        },
        "session_type": {
          "name": "session_type",
          "type": "varchar(100)",
          "primaryKey": false,
          "notNull": true,
          "default": "'JWT (HTTP-only Cookie)'"
        },
        "ip_binding": {
          "name": "ip_binding",
          "type": "boolean",
          "primaryKey": false,
          "notNull": true,
          "default": true
        },
        "password_reset_enforced": {
          "name": "password_reset_enforced",
          "type": "boolean",
          "primaryKey": false,
          "notNull": true,
          "default": true
        },
        "focus_tracking_enabled": {
          "name": "focus_tracking_enabled",
          "type": "boolean",
          "primaryKey": false,
          "notNull": true,
          "default": true
        },
        "auto_save_interval": {
          "name": "auto_save_interval",
          "type": "integer",
          "primaryKey": false,
          "notNull": true,
          "default": 15
        },
        "execution_mode": {
          "name": "execution_mode",
          "type": "varchar(30)",
          "primaryKey": false,
          "notNull": true,
          "default": "'LOCAL_FALLBACK'"
        },
        "updated_at": {
          "name": "updated_at",
          "type": "timestamp with time zone",
          "primaryKey": false,
          "notNull": true,
          "default": "now()"
        }
      },
      "indexes": {},
      "foreignKeys": {},
      "compositePrimaryKeys": {},
      "uniqueConstraints": {},
      "policies": {},
      "checkConstraints": {},
      "isRLSEnabled": false
    },
    "public.questions": {
      "name": "questions",
      "schema": "",
      "columns": {
        "id": {
          "name": "id",
          "type": "uuid",
          "primaryKey": true,
          "notNull": true,
          "default": "gen_random_uuid()"
        },
        "exam_id": {
          "name": "exam_id",
          "type": "uuid",
          "primaryKey": false,
          "notNull": true
        },
        "type": {
          "name": "type",
          "type": "question_type",
          "typeSchema": "public",
          "primaryKey": false,
          "notNull": true
        },
        "title": {
          "name": "title",
          "type": "varchar(150)",
          "primaryKey": false,
          "notNull": true
        },
        "content": {
          "name": "content",
          "type": "text",
          "primaryKey": false,
          "notNull": true
        },
        "points": {
          "name": "points",
          "type": "numeric(5, 2)",
          "primaryKey": false,
          "notNull": true
        },
        "sort_order": {
          "name": "sort_order",
          "type": "integer",
          "primaryKey": false,
          "notNull": true,
          "default": 0
        }
      },
      "indexes": {
        "idx_questions_exam_id": {
          "name": "idx_questions_exam_id",
          "columns": [
            {
              "expression": "exam_id",
              "isExpression": false,
              "asc": true,
              "nulls": "last"
            }
          ],
          "isUnique": false,
          "concurrently": false,
          "method": "btree",
          "with": {}
        }
      },
      "foreignKeys": {
        "questions_exam_id_exams_id_fk": {
          "name": "questions_exam_id_exams_id_fk",
          "tableFrom": "questions",
          "tableTo": "exams",
          "columnsFrom": [
            "exam_id"
          ],
          "columnsTo": [
            "id"
          ],
          "onDelete": "cascade",
          "onUpdate": "no action"
        }
      },
      "compositePrimaryKeys": {},
      "uniqueConstraints": {},
      "policies": {},
      "checkConstraints": {},
      "isRLSEnabled": false
    },
    "public.quiz_options": {
      "name": "quiz_options",
      "schema": "",
      "columns": {
        "id": {
          "name": "id",
          "type": "uuid",
          "primaryKey": true,
          "notNull": true,
          "default": "gen_random_uuid()"
        },
        "question_id": {
          "name": "question_id",
          "type": "uuid",
          "primaryKey": false,
          "notNull": true
        },
        "option_text": {
          "name": "option_text",
          "type": "text",
          "primaryKey": false,
          "notNull": true
        },
        "is_correct": {
          "name": "is_correct",
          "type": "boolean",
          "primaryKey": false,
          "notNull": true,
          "default": false
        }
      },
      "indexes": {
        "idx_quiz_options_question_id": {
          "name": "idx_quiz_options_question_id",
          "columns": [
            {
              "expression": "question_id",
              "isExpression": false,
              "asc": true,
              "nulls": "last"
            }
          ],
          "isUnique": false,
          "concurrently": false,
          "method": "btree",
          "with": {}
        }
      },
      "foreignKeys": {
        "quiz_options_question_id_questions_id_fk": {
          "name": "quiz_options_question_id_questions_id_fk",
          "tableFrom": "quiz_options",
          "tableTo": "questions",
          "columnsFrom": [
            "question_id"
          ],
          "columnsTo": [
            "id"
          ],
          "onDelete": "cascade",
          "onUpdate": "no action"
        }
      },
      "compositePrimaryKeys": {},
      "uniqueConstraints": {},
      "policies": {},
      "checkConstraints": {},
      "isRLSEnabled": false
    },
    "public.submission_details": {
      "name": "submission_details",
      "schema": "",
      "columns": {
        "id": {
          "name": "id",
          "type": "uuid",
          "primaryKey": true,
          "notNull": true,
          "default": "gen_random_uuid()"
        },
        "submission_id": {
          "name": "submission_id",
          "type": "uuid",
          "primaryKey": false,
          "notNull": true
        },
        "question_id": {
          "name": "question_id",
          "type": "uuid",
          "primaryKey": false,
          "notNull": true
        },
        "selected_options": {
          "name": "selected_options",
          "type": "text[]",
          "primaryKey": false,
          "notNull": false,
          "default": "'{}'"
        },
        "source_code": {
          "name": "source_code",
          "type": "text",
          "primaryKey": false,
          "notNull": false
        },
        "language": {
          "name": "language",
          "type": "varchar(30)",
          "primaryKey": false,
          "notNull": false
        },
        "status": {
          "name": "status",
          "type": "execution_status",
          "typeSchema": "public",
          "primaryKey": false,
          "notNull": false
        },
        "student_xpath": {
          "name": "student_xpath",
          "type": "text",
          "primaryKey": false,
          "notNull": false
        },
        "score": {
          "name": "score",
          "type": "numeric(5, 2)",
          "primaryKey": false,
          "notNull": true,
          "default": "'0.00'"
        }
      },
      "indexes": {
        "unique_question_per_submission": {
          "name": "unique_question_per_submission",
          "columns": [
            {
              "expression": "submission_id",
              "isExpression": false,
              "asc": true,
              "nulls": "last"
            },
            {
              "expression": "question_id",
              "isExpression": false,
              "asc": true,
              "nulls": "last"
            }
          ],
          "isUnique": true,
          "concurrently": false,
          "method": "btree",
          "with": {}
        },
        "idx_submission_details_lookup": {
          "name": "idx_submission_details_lookup",
          "columns": [
            {
              "expression": "submission_id",
              "isExpression": false,
              "asc": true,
              "nulls": "last"
            }
          ],
          "isUnique": false,
          "concurrently": false,
          "method": "btree",
          "with": {}
        }
      },
      "foreignKeys": {
        "submission_details_submission_id_exam_submissions_id_fk": {
          "name": "submission_details_submission_id_exam_submissions_id_fk",
          "tableFrom": "submission_details",
          "tableTo": "exam_submissions",
          "columnsFrom": [
            "submission_id"
          ],
          "columnsTo": [
            "id"
          ],
          "onDelete": "cascade",
          "onUpdate": "no action"
        },
        "submission_details_question_id_questions_id_fk": {
          "name": "submission_details_question_id_questions_id_fk",
          "tableFrom": "submission_details",
          "tableTo": "questions",
          "columnsFrom": [
            "question_id"
          ],
          "columnsTo": [
            "id"
          ],
          "onDelete": "cascade",
          "onUpdate": "no action"
        }
      },
      "compositePrimaryKeys": {},
      "uniqueConstraints": {},
      "policies": {},
      "checkConstraints": {},
      "isRLSEnabled": false
    },
    "public.test_cases": {
      "name": "test_cases",
      "schema": "",
      "columns": {
        "id": {
          "name": "id",
          "type": "uuid",
          "primaryKey": true,
          "notNull": true,
          "default": "gen_random_uuid()"
        },
        "question_id": {
          "name": "question_id",
          "type": "uuid",
          "primaryKey": false,
          "notNull": true
        },
        "input_data": {
          "name": "input_data",
          "type": "text",
          "primaryKey": false,
          "notNull": true
        },
        "output_data": {
          "name": "output_data",
          "type": "text",
          "primaryKey": false,
          "notNull": true
        },
        "is_hidden": {
          "name": "is_hidden",
          "type": "boolean",
          "primaryKey": false,
          "notNull": true,
          "default": false
        }
      },
      "indexes": {
        "idx_test_cases_question_id": {
          "name": "idx_test_cases_question_id",
          "columns": [
            {
              "expression": "question_id",
              "isExpression": false,
              "asc": true,
              "nulls": "last"
            }
          ],
          "isUnique": false,
          "concurrently": false,
          "method": "btree",
          "with": {}
        }
      },
      "foreignKeys": {
        "test_cases_question_id_questions_id_fk": {
          "name": "test_cases_question_id_questions_id_fk",
          "tableFrom": "test_cases",
          "tableTo": "questions",
          "columnsFrom": [
            "question_id"
          ],
          "columnsTo": [
            "id"
          ],
          "onDelete": "cascade",
          "onUpdate": "no action"
        }
      },
      "compositePrimaryKeys": {},
      "uniqueConstraints": {},
      "policies": {},
      "checkConstraints": {},
      "isRLSEnabled": false
    },
    "public.users": {
      "name": "users",
      "schema": "",
      "columns": {
        "id": {
          "name": "id",
          "type": "uuid",
          "primaryKey": true,
          "notNull": true,
          "default": "gen_random_uuid()"
        },
        "username": {
          "name": "username",
          "type": "varchar(50)",
          "primaryKey": false,
          "notNull": true
        },
        "password_hash": {
          "name": "password_hash",
          "type": "varchar(255)",
          "primaryKey": false,
          "notNull": true
        },
        "full_name": {
          "name": "full_name",
          "type": "varchar(100)",
          "primaryKey": false,
          "notNull": true
        },
        "email": {
          "name": "email",
          "type": "varchar(100)",
          "primaryKey": false,
          "notNull": true
        },
        "role": {
          "name": "role",
          "type": "user_role",
          "typeSchema": "public",
          "primaryKey": false,
          "notNull": true,
          "default": "'STUDENT'"
        },
        "is_first_login": {
          "name": "is_first_login",
          "type": "boolean",
          "primaryKey": false,
          "notNull": true,
          "default": true
        },
        "created_at": {
          "name": "created_at",
          "type": "timestamp with time zone",
          "primaryKey": false,
          "notNull": true,
          "default": "now()"
        }
      },
      "indexes": {},
      "foreignKeys": {},
      "compositePrimaryKeys": {},
      "uniqueConstraints": {
        "users_username_unique": {
          "name": "users_username_unique",
          "nullsNotDistinct": false,
          "columns": [
            "username"
          ]
        },
        "users_email_unique": {
          "name": "users_email_unique",
          "nullsNotDistinct": false,
          "columns": [
            "email"
          ]
        }
      },
      "policies": {},
      "checkConstraints": {},
      "isRLSEnabled": false
    },
    "public.xpath_configs": {
      "name": "xpath_configs",
      "schema": "",
      "columns": {
        "id": {
          "name": "id",
          "type": "uuid",
          "primaryKey": true,
          "notNull": true,
          "default": "gen_random_uuid()"
        },
        "question_id": {
          "name": "question_id",
          "type": "uuid",
          "primaryKey": false,
          "notNull": true
        },
        "selector_type": {
          "name": "selector_type",
          "type": "varchar(10)",
          "primaryKey": false,
          "notNull": true,
          "default": "'XPATH'"
        }
      },
      "indexes": {},
      "foreignKeys": {
        "xpath_configs_question_id_questions_id_fk": {
          "name": "xpath_configs_question_id_questions_id_fk",
          "tableFrom": "xpath_configs",
          "tableTo": "questions",
          "columnsFrom": [
            "question_id"
          ],
          "columnsTo": [
            "id"
          ],
          "onDelete": "cascade",
          "onUpdate": "no action"
        }
      },
      "compositePrimaryKeys": {},
      "uniqueConstraints": {
        "xpath_configs_question_id_unique": {
          "name": "xpath_configs_question_id_unique",
          "nullsNotDistinct": false,
          "columns": [
            "question_id"
          ]
        }
      },
      "policies": {},
      "checkConstraints": {},
      "isRLSEnabled": false
    },
    "public.xpath_test_cases": {
      "name": "xpath_test_cases",
      "schema": "",
      "columns": {
        "id": {
          "name": "id",
          "type": "uuid",
          "primaryKey": true,
          "notNull": true,
          "default": "gen_random_uuid()"
        },
        "question_id": {
          "name": "question_id",
          "type": "uuid",
          "primaryKey": false,
          "notNull": true
        },
        "target_type": {
          "name": "target_type",
          "type": "varchar(10)",
          "primaryKey": false,
          "notNull": true,
          "default": "'HTML'"
        },
        "selector_type": {
          "name": "selector_type",
          "type": "varchar(10)",
          "primaryKey": false,
          "notNull": true,
          "default": "'XPATH'"
        },
        "target_payload": {
          "name": "target_payload",
          "type": "text",
          "primaryKey": false,
          "notNull": true
        },
        "reference_selector": {
          "name": "reference_selector",
          "type": "text",
          "primaryKey": false,
          "notNull": true
        },
        "is_hidden": {
          "name": "is_hidden",
          "type": "boolean",
          "primaryKey": false,
          "notNull": true,
          "default": false
        }
      },
      "indexes": {
        "idx_xpath_test_cases_question_id": {
          "name": "idx_xpath_test_cases_question_id",
          "columns": [
            {
              "expression": "question_id",
              "isExpression": false,
              "asc": true,
              "nulls": "last"
            }
          ],
          "isUnique": false,
          "concurrently": false,
          "method": "btree",
          "with": {}
        }
      },
      "foreignKeys": {
        "xpath_test_cases_question_id_questions_id_fk": {
          "name": "xpath_test_cases_question_id_questions_id_fk",
          "tableFrom": "xpath_test_cases",
          "tableTo": "questions",
          "columnsFrom": [
            "question_id"
          ],
          "columnsTo": [
            "id"
          ],
          "onDelete": "cascade",
          "onUpdate": "no action"
        }
      },
      "compositePrimaryKeys": {},
      "uniqueConstraints": {},
      "policies": {},
      "checkConstraints": {},
      "isRLSEnabled": false
    }
  },
  "enums": {
    "public.execution_status": {
      "name": "execution_status",
      "schema": "public",
      "values": [
        "AC",
        "WA",
        "CE",
        "RE",
        "TLE",
        "OFE"
      ]
    },
    "public.question_type": {
      "name": "question_type",
      "schema": "public",
      "values": [
        "QUIZ",
        "CODE",
        "XPATH"
      ]
    },
    "public.user_role": {
      "name": "user_role",
      "schema": "public",
      "values": [
        "TEACHER",
        "STUDENT"
      ]
    }
  },
  "schemas": {},
  "sequences": {},
  "roles": {},
  "policies": {},
  "views": {},
  "_meta": {
    "columns": {},
    "schemas": {},
    "tables": {}
  }
}